one_trust/__init__.py
one_trust/file_handle.py
one_trust/main.py
one_trust/ot_class.py
one_trust_55-0.0.19.dist-info/METADATA
one_trust_55-0.0.19.dist-info/WHEEL
one_trust_55-0.0.19.dist-info/top_level.txt
one_trust_55-0.0.19.dist-info/RECORD
